django_forbidden_ip-0.1.dist-info/METADATA
django_forbidden_ip-0.1.dist-info/RECORD
django_forbidden_ip-0.1.dist-info/WHEEL
django_forbidden_ip-0.1.dist-info/top_level.txt
ip_interceptor/__init__.py
ip_interceptor/apps.py
ip_interceptor/middleware.py
ip_interceptor/models.py
