Metadata-Version: 2.1
Name: django-forbidden-ip
Version: 0.1
Summary: IP forbidding utilities for Django2.0
Home-page: https://github.com/jasonqiao36/django-forbidden-ip
Author: Jason Qiao
Author-email: jasonqiao36@gmail.com
License: MIT
Platform: UNKNOWN
Classifier: Development Status :: 3 - Alpha
Classifier: Intended Audience :: Developers
Classifier: Framework :: Django
Classifier: Environment :: Plugins
Classifier: License :: OSI Approved :: MIT License
Classifier: Programming Language :: Python :: 3.6
Requires-Python: >=3.6.0
Requires-Dist: Django (>=2.0)
